MANIFEST.in
README.md
setup.py
cartoonista/__init__.py
cartoonista/cartoonist.py
cartoonista/cartoons.json
cartoonista/commitstrip.py
cartoonista/exceptions.py
cartoonista/explosm.py
cartoonista/islieb.py
cartoonista/jamesofnotrades.py
cartoonista/loadingartist.py
cartoonista/nichtlustig.py
cartoonista/perscheid.py
cartoonista/ruthe.py
cartoonista/schoenescheisse.py
cartoonista/smbc.py
cartoonista/xkcd.py
cartoonista.egg-info/PKG-INFO
cartoonista.egg-info/SOURCES.txt
cartoonista.egg-info/dependency_links.txt
cartoonista.egg-info/requires.txt
cartoonista.egg-info/top_level.txt