Metadata-Version: 2.1
Name: cartoonista
Version: 0.5.1
Summary: A library to get a random cartoon image url from ~20000 cartoons. It also contains the scrapers for many cartoon websites.
Home-page: https://github.com/Netzvamp/cartoonista
Author: Robert Lieback
Author-email: robertlieback@zetabyte.de
License: UNKNOWN
Project-URL: Documentation, https://github.com/Netzvamp/cartoonista
Platform: UNKNOWN
Classifier: Programming Language :: Python :: 3
Classifier: Operating System :: OS Independent
Classifier: Development Status :: 4 - Beta
Classifier: License :: OSI Approved :: MIT License
Classifier: Operating System :: OS Independent
Classifier: Topic :: Games/Entertainment
Requires-Python: >=3.6
Provides-Extra: scraping
